dosp/__init__.py
dosp/client.py
dosp/iptools.py
dosp/protocol.py
dosp/server/__init__.py
dosp/server/base.py
dosp-0.1.3.dist-info/licenses/LICENSE
dosp-0.1.3.dist-info/METADATA
dosp-0.1.3.dist-info/WHEEL
dosp-0.1.3.dist-info/top_level.txt
dosp-0.1.3.dist-info/RECORD
