Metadata-Version: 2.4
Name: DoSP
Version: 0.1.3
Summary: A DoSP (Data over Socket Protocol) client and server
Author-email: daniil10295 <chernyak.daniil.2010@gmail.com>
License-Expression: MIT
Classifier: Development Status :: 4 - Beta
Classifier: Programming Language :: Python :: 3
Classifier: Operating System :: OS Independent
Requires-Python: >=3.8
License-File: LICENSE
Requires-Dist: pycryptodome
Requires-Dist: cryptography
Dynamic: license-file
